{
  "main": {
    "id": "be55df4e0f9a11a2",
    "type": "split",
    "children": [
      {
        "id": "e7a821cf557d88ca",
        "type": "tabs",
        "children": [
          {
            "id": "967c6a58d2a68b3d",
            "type": "leaf",
            "state": {
              "type": "markdown",
              "state": {
                "file": "Software Engingeering/Docker/9. Deploying containers.md",
                "mode": "source",
                "source": false
              },
              "icon": "lucide-file",
              "title": "9. Deploying containers"
            }
          }
        ]
      }
    ],
    "direction": "vertical"
  },
  "left": {
    "id": "7bc4c5536063771e",
    "type": "split",
    "children": [
      {
        "id": "8fdd495c062c791b",
        "type": "tabs",
        "children": [
          {
            "id": "3b62f88b993d7aa6",
            "type": "leaf",
            "state": {
              "type": "file-explorer",
              "state": {
                "sortOrder": "alphabetical"
              },
              "icon": "lucide-folder-closed",
              "title": "Files"
            }
          },
          {
            "id": "e23a2d6fbceb1147",
            "type": "leaf",
            "state": {
              "type": "search",
              "state": {
                "query": "Monolithic",
                "matchingCase": false,
                "explainSearch": false,
                "collapseAll": false,
                "extraContext": false,
                "sortOrder": "alphabetical"
              },
              "icon": "lucide-search",
              "title": "Search"
            }
          },
          {
            "id": "c785c6243c78467c",
            "type": "leaf",
            "state": {
              "type": "bookmarks",
              "state": {},
              "icon": "lucide-bookmark",
              "title": "Bookmarks"
            }
          }
        ]
      }
    ],
    "direction": "horizontal",
    "width": 301.500732421875
  },
  "right": {
    "id": "15640363a29dae7a",
    "type": "split",
    "children": [
      {
        "id": "ea78593425c8b893",
        "type": "tabs",
        "children": [
          {
            "id": "2a4ef359171e1b8a",
            "type": "leaf",
            "state": {
              "type": "backlink",
              "state": {
                "file": "Software Engingeering/Java/7. Web Frameworks/3. JDBC.md",
                "collapseAll": false,
                "extraContext": false,
                "sortOrder": "alphabetical",
                "showSearch": false,
                "searchQuery": "",
                "backlinkCollapsed": false,
                "unlinkedCollapsed": true
              },
              "icon": "links-coming-in",
              "title": "Backlinks for 3. JDBC"
            }
          },
          {
            "id": "be38776ecdc3221b",
            "type": "leaf",
            "state": {
              "type": "outgoing-link",
              "state": {
                "file": "Software Engingeering/Java/7. Web Frameworks/3. JDBC.md",
                "linksCollapsed": false,
                "unlinkedCollapsed": true
              },
              "icon": "links-going-out",
              "title": "Outgoing links from 3. JDBC"
            }
          },
          {
            "id": "c439b7c9e5d25059",
            "type": "leaf",
            "state": {
              "type": "tag",
              "state": {
                "sortOrder": "frequency",
                "useHierarchy": true
              },
              "icon": "lucide-tags",
              "title": "Tags"
            }
          },
          {
            "id": "e876977f6ac2d9d1",
            "type": "leaf",
            "state": {
              "type": "outline",
              "state": {
                "file": "Software Engingeering/Java/7. Web Frameworks/3. JDBC.md"
              },
              "icon": "lucide-list",
              "title": "Outline of 3. JDBC"
            }
          }
        ]
      }
    ],
    "direction": "horizontal",
    "width": 300,
    "collapsed": true
  },
  "left-ribbon": {
    "hiddenItems": {
      "switcher:Open quick switcher": false,
      "graph:Open graph view": false,
      "canvas:Create new canvas": false,
      "daily-notes:Open today's daily note": false,
      "templates:Insert template": false,
      "command-palette:Open command palette": false
    }
  },
  "active": "967c6a58d2a68b3d",
  "lastOpenFiles": [
    "Software Engingeering/Docker/8. Container security.md",
    "Software Engingeering/Docker/9. Deploying containers.md",
    "Software Engingeering/Docker/7. Running containers.md",
    "Software Engingeering/Docker/6. Container registries.md",
    "Software Engingeering/Docker/2. Basics of Docker.md",
    "Software Engingeering/Docker/3. Data Persistence.md",
    "Software Engingeering/Docker/4. 3rd party container images.md",
    "Software Engingeering/Docker/5. Building container images.md",
    "Attachments/img/docker/types-of-mounts-volume.webp",
    "Attachments/img/docker",
    "Software Engingeering/Docker/1. Docker.md",
    "Software Engingeering/Software design and architecture/1. Clean code principles.md",
    "Software Engingeering/Docker",
    "Software Engingeering/Software design and architecture/7. Enterprise Patterns.md",
    "Attachments/img/design-patterns-principles/DTOs.svg",
    "Attachments/img/design-patterns-principles/IdentityMapsPattern.png",
    "Attachments/img/design-patterns-principles/use-case-example.png",
    "Attachments/img/architectural-patterns/UseCases and Functional Tiers.webp",
    "Attachments/img/architectural-patterns/Reposiory-Design-Pattern.png",
    "Software Engingeering/Software design and architecture/6.  Architectural Patterns.md",
    "Software Engingeering/DesignPatterns&Principles/7. Event sourcing/Event Sourcing.md",
    "Attachments/img/design-patterns-principles/queues-vs-streams-vs-pubsub.png",
    "Attachments/img/design-patterns-principles/microkernel.png",
    "Attachments/img/design-patterns-principles/Blackboard-Architecture---1.png",
    "Software Engingeering/Software design and architecture/5. Architectural Styles.md",
    "Attachments/img/design-patterns-principles/cbd.png",
    "Software Engingeering/DesignPatterns&Principles/2. Architectural Patterns/1. Monolithic Apps.md",
    "Software Engingeering/DesignPatterns&Principles/2. Architectural Patterns/Architectural Patterns.md",
    "Software Engingeering/DesignPatterns&Principles/2. Architectural Patterns/6. Twelve Factor Apps.md",
    "Software Engingeering/DesignPatterns&Principles/2. Architectural Patterns/5. Service Mesh.md",
    "Software Engingeering/DesignPatterns&Principles/2. Architectural Patterns/4. Serverless.md",
    "Software Engingeering/DesignPatterns&Principles/2. Architectural Patterns/3. SOA.md",
    "Software Engingeering/DesignPatterns&Principles/3. GOF/GoF Design Patterns.md",
    "Design Patterns.md",
    "Software Engingeering/Software design and architecture/4. Architectural Principles.md",
    "Software Engingeering/Software design and architecture/Untitled",
    "Software Engingeering/Software design and architecture/3. Design principles.md",
    "Software Engingeering/Software design and architecture/2. Programming Paradigms.md",
    "Software Engingeering/Spring Boot/1. Spring Core/3 IOC.md",
    "Software Engingeering/Software design and architecture/Clean code principles",
    "Software Engingeering/Software design and architecture",
    "Attachments/img/building-for-scale",
    "Software Engingeering/Building for scale/Untitled",
    "Software Engingeering/Building for scale/Mitigation Strategies",
    "Software Engingeering/Building for scale/Difference and usage",
    "Software Engingeering/Building for scale",
    "Attachments/canvas/Java/Association.canvas"
  ]
}